kuma/__init__.py
kuma/_logging.py
kuma/constants.py
kuma/kind.py
kuma/private.py
kuma/rest/__init__.py
kuma/rest/_base.py
kuma/rest/active_lists.py
kuma/rest/alerts.py
kuma/rest/assets.py
kuma/rest/context_tables.py
kuma/rest/dictionaries.py
kuma/rest/errors.py
kuma/rest/events.py
kuma/rest/folders.py
kuma/rest/incidents.py
kuma/rest/reports.py
kuma/rest/resources.py
kuma/rest/services.py
kuma/rest/settings.py
kuma/rest/system.py
kuma/rest/tasks.py
kuma/rest/tenants.py
kuma/rest/users.py
kuma_api-3.0.3.dist-info/licenses/LICENSE
kuma_api-3.0.3.dist-info/METADATA
kuma_api-3.0.3.dist-info/WHEEL
kuma_api-3.0.3.dist-info/top_level.txt
kuma_api-3.0.3.dist-info/RECORD
