Metadata-Version: 2.4
Name: kuma-api
Version: 3.0.3
Summary: SDK для работы с API SIEM Kuma
Author-email: Anatolii <mixtol21@gmail.com>
License: MIT License
Project-URL: Homepage, https://support.kaspersky.com/help/KUMA/3.4/en-US/217973.htm
Classifier: Programming Language :: Python :: 3
Classifier: License :: OSI Approved :: MIT License
Classifier: Operating System :: OS Independent
Requires-Python: >=3.9
License-File: LICENSE
Requires-Dist: requests>=2.25.0
Dynamic: license-file
